client/__init__.py
client/client.py
client/client/__init__.py
client/client/database.py
client/client/transport.py
client/client/ui_add_contact.py
client/client/ui_del_contact.py
client/client/ui_main_window.py
client/client/ui_main_window_conv.py
client/client/ui_start.py
client/client/client_models/Base.py
client/client/client_models/Contacts.py
client/client/client_models/KnownUsers.py
client/client/client_models/MessageHistory.py
client/client/client_models/__init__.py
client/common/__init__.py
client/common/decos.py
client/common/descryptors.py
client/common/errors.py
client/common/metaclasses.py
client/common/utils.py
client/common/variables.py
client/logs/__init__.py
client/logs/config_client_log.py
client/logs/config_server_log.py
client/unit_tests/__init__.py
client/unit_tests/test_client.py
client/unit_tests/test_utils.py
client_chat_pyqt_dax-0.0.1.dist-info/METADATA
client_chat_pyqt_dax-0.0.1.dist-info/WHEEL
client_chat_pyqt_dax-0.0.1.dist-info/top_level.txt
client_chat_pyqt_dax-0.0.1.dist-info/RECORD
