Metadata-Version: 2.1
Name: client-chat-pyqt-dax
Version: 0.0.1
Summary: Client packet
Author: Evgeniy Gorbunov
Author-email: test@mail.ru
